dealcloud_api_wrapper/__init__.py
dealcloud_api_wrapper/dc_client.py
dealcloud_api_wrapper/dc_data.py
dealcloud_api_wrapper/dc_schema.py
dealcloud_api_wrapper-0.0.5.dist-info/LICENSE
dealcloud_api_wrapper-0.0.5.dist-info/METADATA
dealcloud_api_wrapper-0.0.5.dist-info/WHEEL
dealcloud_api_wrapper-0.0.5.dist-info/top_level.txt
dealcloud_api_wrapper-0.0.5.dist-info/RECORD
