Metadata-Version: 2.1
Name: dealcloud-api-wrapper
Version: 0.0.5
Summary: A python wrapper for easily interacting with the Dealcloud REST API.
Home-page: https://github.com/geg2102/dealcloud_api_wrapper
Author: Geoffrey Grossman
Author-email: ggrossman1@gmail.com
License: MIT
Platform: UNKNOWN
Classifier: Development Status :: 1 - Planning
Classifier: License :: OSI Approved :: MIT License
Classifier: Programming Language :: Python :: 3
Classifier: Programming Language :: Python :: 3.8
Requires-Dist: requests
Requires-Dist: requests-oauthlib
Requires-Dist: oauthlib
